{
  "source": {
    "type": "github",
    "owner": "Dicklesworthstone",
    "repo": "ntm",
    "channel": "github-release",
    "defaultBranch": "main",
    "tag": "v1.16.0",
    "version": "1.16.0",
    "rev": "8120814150c2a7e4befce79b6fd634a9cdf8599a",
    "hash": "sha256-0gygDlTy4wCUPTkoXkqBeBs8jAl6TwDHKSkVy4CVAR8="
  },
  "package": {
    "repo": "named-tmux-manager",
    "version": "1.16.0"
  },
  "binary": {
    "name": "ntm",
    "package": "cmd/ntm"
  },
  "nix": {
    "goBuilder": "go125",
    "vendorHash": "sha256-srGlFXdP48TfD/84437kk1eUi9HWLKMwVEkzy1OMOMs="
  },
  "meta": {
    "description": "Named Tmux Manager for orchestrating multi-agent tmux workflows",
    "homepage": "https://github.com/Dicklesworthstone/ntm",
    "licenseSpdx": "MIT"
  }
}
